[
	{
		"name":"Galileo arrives at Jupiter",
		"date":"1995-12-07",
		"description":"INSERT DESCRIPTION HERE"
	},
	{
		"name":"Pathfinder and Sojourner land on Mars",
		"date":"1997-07-04",
		"description":"INSERT DESCRIPTION HERE"
	},
	{
		"name":"Spirit lands on Mars",
		"date":"2004-01-04",
		"description":"INSERT DESCRIPTION HERE"
	},
	{
		"name":"Opportunity lands on Mars",
		"date":"2004-01-25",
		"description":"INSERT DESCRIPTION HERE"
	},
	{
		"name":"First manned private space flight by SpaceShipOne",
		"date":"2004-06-21",
		"description":"INSERT DESCRIPTION HERE"
	},
	{
		"name":"First spacecraft to orbit Mercury",
		"date":"2011-03-18",
		"description":"INSERT DESCRIPTION HERE"
	},
	{
		"name":"Curiosity lands on Mars","date":"2012-06-06","description":"INSERT DESCRIPTION HERE"},{"name":"First spacecraft to orbit a comet","date":"2014-06-06","description":"INSERT DESCRIPTION HERE"},{"name":"First spacecraft to land on a comet","date":"2014-11-12","description":"INSERT DESCRIPTION HERE"},{"name":"New Horizons arrives at Pluto","date":"2015-07-14","description":"INSERT DESCRIPTION HERE"},{"name":"Juno arrives at Jupiter","date":"2016-07-04","description":"INSERT DESCRIPTION HERE"
	}
]